easi_py_common/__init__.py
easi_py_common/client/__init__.py
easi_py_common/client/rest_client.py
easi_py_common/client/service_client.py
easi_py_common/core/__init__.py
easi_py_common/core/core.py
easi_py_common/core/env.py
easi_py_common/core/error.py
easi_py_common/core/flasky.py
easi_py_common/core/i18n.py
easi_py_common/core/monkey_doc.py
easi_py_common/core/redis.py
easi_py_common/core/sign_util.py
easi_py_common/core/sql_alchemy.py
easi_py_common/id/__init__.py
easi_py_common/id/id_generator.py
easi_py_common/jwt/__init__.py
easi_py_common/jwt/constants.py
easi_py_common/jwt/jwt.py
easi_py_common/s3/__init__.py
easi_py_common/s3/s3.py
easi_py_common/secretsmanager/__init__.py
easi_py_common/secretsmanager/secretsmanager.py
easi_py_common/sqs/__init__.py
easi_py_common/sqs/constants.py
easi_py_common/sqs/consumer.py
easi_py_common/sqs/decorator.py
easi_py_common/sqs/log_sqs.py
easi_py_common/sqs/producer.py
easi_py_common/sqs/producer_session.py
easi_py_common/sqs/sqs.py
easi_py_common/sqs/utils.py
easi_py_common/util/__init__.py
easi_py_common/util/list_util.py
easi_py_common-0.0.76.dist-info/WHEEL
easi_py_common-0.0.76.dist-info/METADATA
easi_py_common-0.0.76.dist-info/RECORD
