Metadata-Version: 2.1
Name: easi-py-common
Version: 0.0.76
Summary: 
Home-page: https://poetry.eustace.io/
License: MIT
Author: wangziqing
Author-email: eininst@aliyun.com
Requires-Python: >=3.8,<4.0
Classifier: License :: OSI Approved :: MIT License
Classifier: Programming Language :: Python :: 3
Classifier: Programming Language :: Python :: 3.8
Classifier: Programming Language :: Python :: 3.9
Requires-Dist: boto3 (==1.16.19)
Requires-Dist: flask (==1.1.2)
Requires-Dist: flask-redis (==0.4.0)
Requires-Dist: flask-sqlalchemy (==2.4.4)
Requires-Dist: flask-uploads (==0.2.1)
Requires-Dist: flask-wtf (==0.14.3)
Requires-Dist: flaskerk (==0.6.3)
Requires-Dist: gevent (==20.9.0)
Requires-Dist: itsdangerous (==1.1.0)
Requires-Dist: orjson (==3.4.6)
Requires-Dist: pip (==21.0.1)
Requires-Dist: pydantic (==1.7.2)
Requires-Dist: pymysql (==0.10.1)
Requires-Dist: pytz (==2020.4)
Requires-Dist: pyyaml (==5.3.1)
Requires-Dist: requests (==2.25.0)
Requires-Dist: sqlalchemy (==1.3.24)
Requires-Dist: werkzeug (==1.0.1)
Project-URL: Documentation, https://github.com/infinitasx/easi-py-common
Project-URL: Repository, https://github.com/infinitasx/easi-py-common
